[
    {
        "id": 2,
        "display_name": "Autocannon I",
        "name": "autocannon-1",
        "range": 10,
        "ap": "D4",
        "at": "D4",
        "aa": "D4",
        "damage": "L",
        "cost_d4": 1,
        "cost_d6": 1,
        "cost_d8": 1,
        "cost_d10": 1,
        "cost_d12": 1
    },
    {
        "id": 3,
        "display_name": "Autocannon II",
        "name": "autocannon-2",
        "range": 14,
        "ap": "D6",
        "at": "D6",
        "aa": "D6",
        "damage": "ML",
        "cost_d4": 1,
        "cost_d6": 2,
        "cost_d8": 3,
        "cost_d10": 4,
        "cost_d12": 4
    },
    {
        "id": 4,
        "display_name": "Autocannon III",
        "name": "autocannon-3",
        "range": 180,
        "ap": "D8",
        "at": "D8",
        "aa": "D8",
        "damage": "ML",
        "cost_d4": 3,
        "cost_d6": 4,
        "cost_d8": 5,
        "cost_d10": 6,
        "cost_d12": 6
    },
    {
        "id": 5,
        "display_name": "Autocannon IV",
        "name": "autocannon-4",
        "range": 22,
        "ap": "D10",
        "at": "D10",
        "aa": "D10",
        "damage": "MH",
        "cost_d4": 5,
        "cost_d6": 6,
        "cost_d8": 7,
        "cost_d10": 8,
        "cost_d12": 9
    },
    {
        "id": 6,
        "display_name": "Autocannon V",
        "name": "autocannon-5",
        "range": 26,
        "ap": "D12",
        "at": "D12",
        "aa": "D12",
        "damage": "H",
        "cost_d4": 9,
        "cost_d6": 10,
        "cost_d8": 11,
        "cost_d10": 13,
        "cost_d12": 14
    },
    {
        "id": 7,
        "display_name": "Bombs I",
        "name": "bombs-1",
        "range": 0,
        "ap": "D4",
        "at": "D4",
        "aa": "D4",
        "damage": "L",
        "cost_d4": 1,
        "cost_d6": 1,
        "cost_d8": 1,
        "cost_d10": 1,
        "cost_d12": 1,
        "has_warheads": true
    },
    {
        "id": 8,
        "display_name": "Bombs II",
        "name": "bombs-2",
        "range": 0,
        "ap": "D6",
        "at": "D6",
        "aa": "D6",
        "damage": "ML",
        "cost_d4": 1,
        "cost_d6": 1,
        "cost_d8": 1,
        "cost_d10": 1,
        "cost_d12": 1,
        "has_warheads": true
    },
    {
        "id": 9,
        "display_name": "Bombs III",
        "name": "bombs-3",
        "range": 0,
        "ap": "D8",
        "at": "D8",
        "aa": "D8",
        "damage": "MH",
        "cost_d4": 1,
        "cost_d6": 1,
        "cost_d8": 1,
        "cost_d10": 1,
        "cost_d12": 1,
        "has_warheads": true
    },
    {
        "id": 10,
        "display_name": "Bombs IV",
        "name": "bombs-4",
        "range": 0,
        "ap": "D10",
        "at": "D10",
        "aa": "D10",
        "damage": "MH",
        "cost_d4": 1,
        "cost_d6": 1,
        "cost_d8": 1,
        "cost_d10": 1,
        "cost_d12": 1,
        "has_warheads": true
    },
    {
        "id": 11,
        "display_name": "Bombs V",
        "name": "bombs-5",
        "range": 0,
        "ap": "D12",
        "at": "D12",
        "aa": "D12",
        "damage": "H",
        "cost_d4": 1,
        "cost_d6": 1,
        "cost_d8": 2,
        "cost_d10": 2,
        "cost_d12": 2,
        "has_warheads": true
    },
    {
        "id": 12,
        "display_name": "Chemical Spray I",
        "name": "chemical-spray-1",
        "range": 2,
        "ap": "D8",
        "at": "D4",
        "aa": "D4",
        "damage": "L",
        "cost_d4": 1,
        "cost_d6": 1,
        "cost_d8": 1,
        "cost_d10": 1,
        "cost_d12": 1
    },
    {
        "id": 13,
        "display_name": "Chemical Spray II",
        "name": "chemical-spray-2",
        "range": 3,
        "ap": "D8",
        "at": "D4",
        "aa": "D4",
        "damage": "L",
        "cost_d4": 1,
        "cost_d6": 1,
        "cost_d8": 1,
        "cost_d10": 1,
        "cost_d12": 1
    },
    {
        "id": 14,
        "display_name": "Chemical Spray III",
        "name": "chemical-spray-3",
        "range": 4,
        "ap": "D10",
        "at": "D6",
        "aa": "D6",
        "damage": "L",
        "cost_d4": 1,
        "cost_d6": 1,
        "cost_d8": 1,
        "cost_d10": 1,
        "cost_d12": 2
    },
    {
        "id": 15,
        "display_name": "Chemical Spray IV",
        "name": "chemical-spray-4",
        "range": 5,
        "ap": "D12",
        "at": "D8",
        "aa": "D8",
        "damage": "ML",
        "cost_d4": 2,
        "cost_d6": 2,
        "cost_d8": 2,
        "cost_d10": 3,
        "cost_d12": 3
    },
    {
        "id": 16,
        "display_name": "Chemical Spray V",
        "name": "chemical-spray-5",
        "range": 6,
        "ap": "D12",
        "at": "D8",
        "aa": "D8",
        "damage": "MH",
        "cost_d4": 2,
        "cost_d6": 2,
        "cost_d8": 3,
        "cost_d10": 3,
        "cost_d12": 4
    },
    {
        "id": 17,
        "display_name": "Conventional Gun I",
        "name": "conventional-gun-1",
        "range": 12,
        "ap": "D4",
        "at": "D4",
        "aa": "D4",
        "damage": "L",
        "cost_d4": 1,
        "cost_d6": 1,
        "cost_d8": 1,
        "cost_d10": 1,
        "cost_d12": 2
    },
    {
        "id": 18,
        "display_name": "Conventional Gun II",
        "name": "conventional-gun-2",
        "range": 16,
        "ap": "D4",
        "at": "D6",
        "aa": "D6",
        "damage": "ML",
        "cost_d4": 1,
        "cost_d6": 2,
        "cost_d8": 3,
        "cost_d10": 4,
        "cost_d12": 5
    },
    {
        "id": 19,
        "display_name": "Conventional Gun III",
        "name": "conventional-gun-3",
        "range": 20,
        "ap": "D6",
        "at": "D8",
        "aa": "D8",
        "damage": "MH",
        "cost_d4": 3,
        "cost_d6": 4,
        "cost_d8": 5,
        "cost_d10": 6,
        "cost_d12": 7
    },
    {
        "id": 20,
        "display_name": "Conventional Gun IV",
        "name": "conventional-gun-4",
        "range": 24,
        "ap": "D8",
        "at": "D10",
        "aa": "D10",
        "damage": "MH",
        "cost_d4": 4,
        "cost_d6": 6,
        "cost_d8": 7,
        "cost_d10": 9,
        "cost_d12": 10
    },
    {
        "id": 21,
        "display_name": "Conventional Gun V",
        "name": "conventional-gun-5",
        "range": 28,
        "ap": "D10",
        "at": "D12",
        "aa": "D12",
        "damage": "H",
        "cost_d4": 8,
        "cost_d6": 10,
        "cost_d8": 11,
        "cost_d10": 13,
        "cost_d12": 15
    },
    {
        "id": 22,
        "display_name": "Flamethrower I",
        "name": "flamethrower-1",
        "range": 2,
        "ap": "D8",
        "at": "D4",
        "aa": "D4",
        "damage": "L",
        "cost_d4": 1,
        "cost_d6": 1,
        "cost_d8": 1,
        "cost_d10": 1,
        "cost_d12": 1
    },
    {
        "id": 23,
        "display_name": "Flamethrower II",
        "name": "flamethrower-2",
        "range": 3,
        "ap": "D8",
        "at": "D4",
        "aa": "D4",
        "damage": "ML",
        "cost_d4": 1,
        "cost_d6": 1,
        "cost_d8": 1,
        "cost_d10": 2,
        "cost_d12": 2
    },
    {
        "id": 24,
        "display_name": "Flamethrower III",
        "name": "flamethrower-3",
        "range": 4,
        "ap": "D10",
        "at": "D6",
        "aa": "D6",
        "damage": "MH",
        "cost_d4": 1,
        "cost_d6": 2,
        "cost_d8": 2,
        "cost_d10": 2,
        "cost_d12": 3
    },
    {
        "id": 25,
        "display_name": "Flamethrower IV",
        "name": "flamethrower-4",
        "range": 5,
        "ap": "D12",
        "at": "D8",
        "aa": "D8",
        "damage": "MH",
        "cost_d4": 2,
        "cost_d6": 2,
        "cost_d8": 3,
        "cost_d10": 3,
        "cost_d12": 3
    },
    {
        "id": 26,
        "display_name": "Flamethrower V",
        "name": "flamethrower-5",
        "range": 6,
        "ap": "D12",
        "at": "D8",
        "aa": "D8",
        "damage": "H",
        "cost_d4": 2,
        "cost_d6": 3,
        "cost_d8": 3,
        "cost_d10": 4,
        "cost_d12": 5
    },
    {
        "id": 27,
        "display_name": "Howitzer I",
        "name": "howitzer-1",
        "range": 20,
        "ap": "D4",
        "at": "D4",
        "aa": "D4",
        "damage": "H*",
        "cost_d4": 1,
        "cost_d6": 2,
        "cost_d8": 3,
        "cost_d10": 5,
        "cost_d12": 7,
        "has_warheads": true,
        "is_indirect": true
    },
    {
        "id": 28,
        "display_name": "Howitzer II",
        "name": "howitzer-2",
        "range": 30,
        "ap": "D6",
        "at": "D6",
        "aa": "D6",
        "damage": "H*",
        "cost_d4": 3,
        "cost_d6": 5,
        "cost_d8": 7,
        "cost_d10": 10,
        "cost_d12": 12,
        "has_warheads": true,
        "is_indirect": true
    },
    {
        "id": 29,
        "display_name": "Howitzer III",
        "name": "howitzer-3",
        "range": 40,
        "ap": "D8",
        "at": "D8",
        "aa": "D8",
        "damage": "H*",
        "cost_d4": 6,
        "cost_d6": 9,
        "cost_d8": 11,
        "cost_d10": 15,
        "cost_d12": 18,
        "has_warheads": true,
        "is_indirect": true
    },
    {
        "id": 30,
        "display_name": "Howitzer IV",
        "name": "howitzer-4",
        "range": 50,
        "ap": "D10",
        "at": "D10",
        "aa": "D10",
        "damage": "H*",
        "cost_d4": 13,
        "cost_d6": 17,
        "cost_d8": 20,
        "cost_d10": 25,
        "cost_d12": 28,
        "has_warheads": true,
        "is_indirect": true
    },
    {
        "id": 31,
        "display_name": "Howitzer V",
        "name": "howitzer-5",
        "range": 60,
        "ap": "D12",
        "at": "D12",
        "aa": "D12",
        "damage": "H*",
        "cost_d4": 24,
        "cost_d6": 28,
        "cost_d8": 32,
        "cost_d10": 36,
        "cost_d12": 41,
        "has_warheads": true,
        "is_indirect": true
    },
    {
        "id": 32,
        "display_name": "Chem. Spray I",
        "name": "inf-chem-spray-1",
        "range": 2,
        "ap": "D6",
        "at": "D4",
        "aa": "D4",
        "damage": "L",
        "cost_d4": 1,
        "cost_d6": 1,
        "cost_d8": 1,
        "cost_d10": 1,
        "cost_d12": 1,
        "infantry": true
    },
    {
        "id": 33,
        "display_name": "Chem. Spray II",
        "name": "inf-chem-spray-2",
        "range": 3,
        "ap": "D8",
        "at": "D6",
        "aa": "D6",
        "damage": "L",
        "cost_d4": 1,
        "cost_d6": 1,
        "cost_d8": 1,
        "cost_d10": 1,
        "cost_d12": 1,
        "infantry": true
    },
    {
        "id": 34,
        "display_name": "Chem. Spray III",
        "name": "inf-chem-spray-3",
        "range": 4,
        "ap": "D10",
        "at": "D8",
        "aa": "D8",
        "damage": "ML",
        "cost_d4": 1,
        "cost_d6": 2,
        "cost_d8": 2,
        "cost_d10": 2,
        "cost_d12": 3,
        "infantry": true
    },
    {
        "id": 35,
        "display_name": "Flamethrower I",
        "name": "inf-flamethrower-1",
        "range": 2,
        "ap": "D8",
        "at": "D4",
        "aa": "D4",
        "damage": "ML",
        "cost_d4": 1,
        "cost_d6": 1,
        "cost_d8": 1,
        "cost_d10": 1,
        "cost_d12": 2,
        "infantry": true
    },
    {
        "id": 36,
        "display_name": "Flamethrower II",
        "name": "inf-flamethrower-2",
        "range": 3,
        "ap": "D8",
        "at": "D4",
        "aa": "D4",
        "damage": "ML",
        "cost_d4": 1,
        "cost_d6": 1,
        "cost_d8": 1,
        "cost_d10": 2,
        "cost_d12": 2,
        "infantry": true
    },
    {
        "id": 37,
        "display_name": "Flamethrower III",
        "name": "inf-flamethrower-3",
        "range": 4,
        "ap": "D10",
        "at": "D6",
        "aa": "D6",
        "damage": "MH",
        "cost_d4": 1,
        "cost_d6": 2,
        "cost_d8": 2,
        "cost_d10": 2,
        "cost_d12": 3,
        "infantry": true
    },
    {
        "id": 38,
        "display_name": "Laser I",
        "name": "inf-laser-1",
        "range": 24,
        "ap": "D6",
        "at": "D4",
        "aa": "D4",
        "damage": "ML",
        "cost_d4": 2,
        "cost_d6": 3,
        "cost_d8": 4,
        "cost_d10": 5,
        "cost_d12": 6,
        "infantry": true
    },
    {
        "id": 39,
        "display_name": "Laser II",
        "name": "inf-laser-2",
        "range": 30,
        "ap": "D8",
        "at": "D6",
        "aa": "D6",
        "damage": "MH",
        "cost_d4": 4,
        "cost_d6": 5,
        "cost_d8": 7,
        "cost_d10": 9,
        "cost_d12": 10,
        "infantry": true
    },
    {
        "id": 40,
        "display_name": "Laser III",
        "name": "inf-laser-3",
        "range": 36,
        "ap": "D10",
        "at": "D8",
        "aa": "D8",
        "damage": "H",
        "cost_d4": 6,
        "cost_d6": 8,
        "cost_d8": 10,
        "cost_d10": 13,
        "cost_d12": 16,
        "infantry": true
    },
    {
        "id": 41,
        "display_name": "Laser Small Arms I",
        "name": "inf-laser-small-arms-1",
        "range": 12,
        "ap": "D4",
        "at": "D4",
        "aa": "D4",
        "damage": "L",
        "cost_d4": 1,
        "cost_d6": 1,
        "cost_d8": 1,
        "cost_d10": 1,
        "cost_d12": 2,
        "infantry": true
    },
    {
        "id": 42,
        "display_name": "Laser Small Arms II",
        "name": "inf-laser-small-arms-2",
        "range": 14,
        "ap": "D4",
        "at": "D6",
        "aa": "D6",
        "damage": "L",
        "cost_d4": 1,
        "cost_d6": 1,
        "cost_d8": 2,
        "cost_d10": 2,
        "cost_d12": 2,
        "infantry": true
    },
    {
        "id": 43,
        "display_name": "Laser Small Arms III",
        "name": "inf-laser-small-arms-3",
        "range": 16,
        "ap": "D6",
        "at": "D8",
        "aa": "D8",
        "damage": "ML",
        "cost_d4": 2,
        "cost_d6": 3,
        "cost_d8": 4,
        "cost_d10": 5,
        "cost_d12": 5,
        "infantry": true
    },
    {
        "id": 44,
        "display_name": "Machine Gun I",
        "name": "inf-machine-gun-1",
        "range": 7,
        "ap": "D6",
        "at": "D4",
        "aa": "D4",
        "damage": "L",
        "cost_d4": 1,
        "cost_d6": 1,
        "cost_d8": 1,
        "cost_d10": 1,
        "cost_d12": 1,
        "infantry": true
    },
    {
        "id": 45,
        "display_name": "Machine Gun II",
        "name": "inf-machine-gun-2",
        "range": 10,
        "ap": "D8",
        "at": "D6",
        "aa": "D6",
        "damage": "L",
        "cost_d4": 1,
        "cost_d6": 2,
        "cost_d8": 2,
        "cost_d10": 2,
        "cost_d12": 2,
        "infantry": true
    },
    {
        "id": 46,
        "display_name": "Machine Gun III",
        "name": "inf-machine-gun-3",
        "range": 13,
        "ap": "D10",
        "at": "D8",
        "aa": "D8",
        "damage": "ML",
        "cost_d4": 2,
        "cost_d6": 3,
        "cost_d8": 4,
        "cost_d10": 5,
        "cost_d12": 5,
        "infantry": true
    },
    {
        "id": 47,
        "display_name": "Missile Launcher I",
        "name": "inf-missile-launcher-1",
        "range": 20,
        "ap": "D4",
        "at": "D6",
        "aa": "D6",
        "damage": "L",
        "cost_d4": 1,
        "cost_d6": 2,
        "cost_d8": 2,
        "cost_d10": 3,
        "cost_d12": 3,
        "infantry": true
    },
    {
        "id": 48,
        "display_name": "Missile Launcher II",
        "name": "inf-missile-launcher-2",
        "range": 24,
        "ap": "D6",
        "at": "D8",
        "aa": "D8",
        "damage": "ML",
        "cost_d4": 3,
        "cost_d6": 4,
        "cost_d8": 5,
        "cost_d10": 7,
        "cost_d12": 8,
        "infantry": true
    },
    {
        "id": 49,
        "display_name": "Missile Launcher III",
        "name": "inf-missile-launcher-3",
        "range": 28,
        "ap": "D8",
        "at": "D10",
        "aa": "D10",
        "damage": "MH",
        "cost_d4": 5,
        "cost_d6": 7,
        "cost_d8": 9,
        "cost_d10": 10,
        "cost_d12": 12,
        "infantry": true
    },
    {
        "id": 50,
        "display_name": "Mortar I",
        "name": "inf-mortar-1",
        "range": 10,
        "ap": "D4",
        "at": "D4",
        "aa": "D4",
        "damage": "ML",
        "cost_d4": 1,
        "cost_d6": 1,
        "cost_d8": 2,
        "cost_d10": 2,
        "cost_d12": 3,
        "infantry": true,
        "is_indirect": true
    },
    {
        "id": 51,
        "display_name": "Mortar II",
        "name": "inf-mortar-2",
        "range": 14,
        "ap": "D4",
        "at": "D4",
        "aa": "D4",
        "damage": "ML",
        "cost_d4": 1,
        "cost_d6": 2,
        "cost_d8": 2,
        "cost_d10": 3,
        "cost_d12": 4,
        "infantry": true,
        "is_indirect": true
    },
    {
        "id": 52,
        "display_name": "Mortar III",
        "name": "inf-mortar-3",
        "range": 18,
        "ap": "D6",
        "at": "D6",
        "aa": "D6",
        "damage": "MH",
        "cost_d4": 2,
        "cost_d6": 3,
        "cost_d8": 4,
        "cost_d10": 5,
        "cost_d12": 6,
        "infantry": true,
        "is_indirect": true
    },
    {
        "id": 53,
        "display_name": "Plasma I",
        "name": "inf-plasma-1",
        "range": 4,
        "ap": "D8",
        "at": "D8",
        "aa": "D8",
        "damage": "ML",
        "cost_d4": 1,
        "cost_d6": 2,
        "cost_d8": 2,
        "cost_d10": 2,
        "cost_d12": 2,
        "infantry": true
    },
    {
        "id": 54,
        "display_name": "Plasma II",
        "name": "inf-plasma-2",
        "range": 5,
        "ap": "D10",
        "at": "D10",
        "aa": "D10",
        "damage": "ML",
        "cost_d4": 2,
        "cost_d6": 2,
        "cost_d8": 2,
        "cost_d10": 3,
        "cost_d12": 3,
        "infantry": true
    },
    {
        "id": 55,
        "display_name": "Plasma III",
        "name": "inf-plasma-3",
        "range": 6,
        "ap": "D12",
        "at": "D12",
        "aa": "D12",
        "damage": "MH",
        "cost_d4": 2,
        "cost_d6": 3,
        "cost_d8": 3,
        "cost_d10": 4,
        "cost_d12": 4,
        "infantry": true
    },
    {
        "id": 56,
        "display_name": "Pulse Laser I",
        "name": "inf-pulse-laser-1",
        "range": 24,
        "ap": "D4",
        "at": "D4",
        "aa": "D4",
        "damage": "L",
        "cost_d4": 1,
        "cost_d6": 1,
        "cost_d8": 2,
        "cost_d10": 2,
        "cost_d12": 2,
        "infantry": true
    },
    {
        "id": 57,
        "display_name": "Pulse Laser II",
        "name": "inf-pulse-laser-2",
        "range": 30,
        "ap": "D6",
        "at": "D4",
        "aa": "D4",
        "damage": "L",
        "cost_d4": 1,
        "cost_d6": 2,
        "cost_d8": 3,
        "cost_d10": 3,
        "cost_d12": 4,
        "infantry": true
    },
    {
        "id": 58,
        "display_name": "Pulse Laser III",
        "name": "inf-pulse-laser-3",
        "range": 36,
        "ap": "D8",
        "at": "D4",
        "aa": "D4",
        "damage": "L",
        "cost_d4": 2,
        "cost_d6": 3,
        "cost_d8": 4,
        "cost_d10": 5,
        "cost_d12": 5,
        "infantry": true
    },
    {
        "id": 59,
        "display_name": "Small Arms I",
        "name": "inf-small-arms-1",
        "range": 6,
        "ap": "D4",
        "at": "D4",
        "aa": "D4",
        "damage": "L",
        "cost_d4": 1,
        "cost_d6": 1,
        "cost_d8": 1,
        "cost_d10": 1,
        "cost_d12": 1,
        "infantry": true
    },
    {
        "id": 60,
        "display_name": "Small Arms II",
        "name": "inf-small-arms-2",
        "range": 8,
        "ap": "D6",
        "at": "D6",
        "aa": "D6",
        "damage": "ML",
        "cost_d4": 1,
        "cost_d6": 2,
        "cost_d8": 2,
        "cost_d10": 3,
        "cost_d12": 3,
        "infantry": true
    },
    {
        "id": 61,
        "display_name": "Small Arms III",
        "name": "inf-small-arms-3",
        "range": 10,
        "ap": "D8",
        "at": "D8",
        "aa": "D8",
        "damage": "MH",
        "cost_d4": 2,
        "cost_d6": 3,
        "cost_d8": 3,
        "cost_d10": 4,
        "cost_d12": 4,
        "infantry": true
    },
    {
        "id": 62,
        "display_name": "Laser I",
        "name": "laser-1",
        "range": 30,
        "ap": "D6",
        "at": "D6",
        "aa": "D6",
        "damage": "ML",
        "cost_d4": 2,
        "cost_d6": 4,
        "cost_d8": 6,
        "cost_d10": 7,
        "cost_d12": 8
    },
    {
        "id": 63,
        "display_name": "Laser II",
        "name": "laser-2",
        "range": 34,
        "ap": "D6",
        "at": "D8",
        "aa": "D8",
        "damage": "ML",
        "cost_d4": 3,
        "cost_d6": 5,
        "cost_d8": 7,
        "cost_d10": 9,
        "cost_d12": 10
    },
    {
        "id": 64,
        "display_name": "Laser III",
        "name": "laser-3",
        "range": 38,
        "ap": "D8",
        "at": "D8",
        "aa": "D8",
        "damage": "MH",
        "cost_d4": 5,
        "cost_d6": "",
        "cost_d8": 10,
        "cost_d10": 12,
        "cost_d12": 13
    },
    {
        "id": 65,
        "display_name": "Laser IV",
        "name": "laser-4",
        "range": 42,
        "ap": "D8",
        "at": "D10",
        "aa": "D10",
        "damage": "H",
        "cost_d4": 8,
        "cost_d6": 11,
        "cost_d8": 13,
        "cost_d10": 17,
        "cost_d12": 19
    },
    {
        "id": 66,
        "display_name": "Laser V",
        "name": "laser-5",
        "range": 46,
        "ap": "D10",
        "at": "D12",
        "aa": "D12",
        "damage": "H",
        "cost_d4": 13,
        "cost_d6": 15,
        "cost_d8": 18,
        "cost_d10": 21,
        "cost_d12": 24
    },
    {
        "id": 67,
        "display_name": "Machine Gun I",
        "name": "machine-gun-1",
        "range": 8,
        "ap": "D6",
        "at": "D4",
        "aa": "D4",
        "damage": "L",
        "cost_d4": 1,
        "cost_d6": 1,
        "cost_d8": 1,
        "cost_d10": 1,
        "cost_d12": 2
    },
    {
        "id": 68,
        "display_name": "Machine Gun II",
        "name": "machine-gun-2",
        "range": 10,
        "ap": "D8",
        "at": "D6",
        "aa": "D6",
        "damage": "L",
        "cost_d4": 1,
        "cost_d6": 2,
        "cost_d8": 2,
        "cost_d10": 2,
        "cost_d12": 2
    },
    {
        "id": 69,
        "display_name": "Machine Gun III",
        "name": "machine-gun-3",
        "range": 12,
        "ap": "D8",
        "at": "D6",
        "aa": "D6",
        "damage": "ML",
        "cost_d4": 2,
        "cost_d6": 2,
        "cost_d8": 3,
        "cost_d10": 4,
        "cost_d12": 4
    },
    {
        "id": 70,
        "display_name": "Machine Gun IV",
        "name": "machine-gun-4",
        "range": 14,
        "ap": "D10",
        "at": "D8",
        "aa": "D8",
        "damage": "ML",
        "cost_d4": 3,
        "cost_d6": 3,
        "cost_d8": 4,
        "cost_d10": 5,
        "cost_d12": 5
    },
    {
        "id": 71,
        "display_name": "Machine Gun V",
        "name": "machine-gun-5",
        "range": 16,
        "ap": "D10",
        "at": "D8",
        "aa": "D8",
        "damage": "MH",
        "cost_d4": 3,
        "cost_d6": 4,
        "cost_d8": 5,
        "cost_d10": 6,
        "cost_d12": 7
    },
    {
        "id": 72,
        "display_name": "Missile I",
        "name": "missile-1",
        "range": 20,
        "ap": "D4",
        "at": "D6",
        "aa": "D6",
        "damage": "ML",
        "cost_d4": 1,
        "cost_d6": 2,
        "cost_d8": 3,
        "cost_d10": 5,
        "cost_d12": 6,
        "has_warheads": true,
        "is_indirect": true
    },
    {
        "id": 73,
        "display_name": "Missile II",
        "name": "missile-2",
        "range": 30,
        "ap": "D6",
        "at": "D8",
        "aa": "D8",
        "damage": "MH",
        "cost_d4": 4,
        "cost_d6": 6,
        "cost_d8": 8,
        "cost_d10": 9,
        "cost_d12": 11,
        "has_warheads": true,
        "is_indirect": true
    },
    {
        "id": 74,
        "display_name": "Missile III",
        "name": "missile-3",
        "range": 40,
        "ap": "D8",
        "at": "D10",
        "aa": "D10",
        "damage": "MH",
        "cost_d4": 7,
        "cost_d6": 10,
        "cost_d8": 13,
        "cost_d10": 15,
        "cost_d12": 17,
        "has_warheads": true,
        "is_indirect": true
    },
    {
        "id": 75,
        "display_name": "Missile IV",
        "name": "missile-4",
        "range": 50,
        "ap": "D10",
        "at": "D12",
        "aa": "D12",
        "damage": "MH",
        "cost_d4": 13,
        "cost_d6": 16,
        "cost_d8": 20,
        "cost_d10": 23,
        "cost_d12": 26,
        "has_warheads": true,
        "is_indirect": true
    },
    {
        "id": 76,
        "display_name": "Missile V",
        "name": "missile-5",
        "range": 60,
        "ap": "D12",
        "at": "D12",
        "aa": "D12",
        "damage": "H",
        "cost_d4": 24,
        "cost_d6": 29,
        "cost_d8": 33,
        "cost_d10": 38,
        "cost_d12": 42,
        "has_warheads": true,
        "is_indirect": true
    },
    {
        "id": 77,
        "display_name": "Mortar I",
        "name": "mortar-1",
        "range": 12,
        "ap": "D4",
        "at": "D4",
        "aa": "D4",
        "damage": "ML",
        "cost_d4": 1,
        "cost_d6": 1,
        "cost_d8": 2,
        "cost_d10": 3,
        "cost_d12": 3,
        "is_indirect": true
    },
    {
        "id": 78,
        "display_name": "Mortar II",
        "name": "mortar-2",
        "range": 18,
        "ap": "D4",
        "at": "D6",
        "aa": "D6",
        "damage": "ML",
        "cost_d4": 1,
        "cost_d6": 2,
        "cost_d8": 3,
        "cost_d10": 4,
        "cost_d12": 5,
        "is_indirect": true
    },
    {
        "id": 79,
        "display_name": "Mortar III",
        "name": "mortar-3",
        "range": 24,
        "ap": "D6",
        "at": "D6",
        "aa": "D6",
        "damage": "MH",
        "cost_d4": 2,
        "cost_d6": 4,
        "cost_d8": 5,
        "cost_d10": 7,
        "cost_d12": 8,
        "is_indirect": true
    },
    {
        "id": 80,
        "display_name": "Mortar IV",
        "name": "mortar-4",
        "range": 30,
        "ap": "D6",
        "at": "D8",
        "aa": "D8",
        "damage": "MH",
        "cost_d4": 4,
        "cost_d6": 5,
        "cost_d8": 7,
        "cost_d10": 9,
        "cost_d12": 10,
        "is_indirect": true
    },
    {
        "id": 81,
        "display_name": "Mortar V",
        "name": "mortar-5",
        "range": 36,
        "ap": "D8",
        "at": "D8",
        "aa": "D8",
        "damage": "H",
        "cost_d4": 5,
        "cost_d6": 8,
        "cost_d8": 10,
        "cost_d10": 13,
        "cost_d12": 16,
        "is_indirect": true
    },
    {
        "id": 82,
        "display_name": "Particle Bolter I",
        "name": "particle-bolter-1",
        "range": 10,
        "ap": "D4",
        "at": "D4",
        "aa": "D4",
        "damage": "ML",
        "cost_d4": 1,
        "cost_d6": 1,
        "cost_d8": 2,
        "cost_d10": 3,
        "cost_d12": 3
    },
    {
        "id": 83,
        "display_name": "Particle Bolter II",
        "name": "particle-bolter-2",
        "range": 16,
        "ap": "D4",
        "at": "D4",
        "aa": "D4",
        "damage": "MH",
        "cost_d4": 1,
        "cost_d6": 2,
        "cost_d8": 3,
        "cost_d10": 4,
        "cost_d12": 5
    },
    {
        "id": 84,
        "display_name": "Particle Bolter III",
        "name": "particle-bolter-3",
        "range": 22,
        "ap": "D6",
        "at": "D6",
        "aa": "D6",
        "damage": "MH",
        "cost_d4": 3,
        "cost_d6": 4,
        "cost_d8": 6,
        "cost_d10": 7,
        "cost_d12": 9
    },
    {
        "id": 85,
        "display_name": "Particle Bolter IV",
        "name": "particle-bolter-4",
        "range": 28,
        "ap": "D6",
        "at": "D6",
        "aa": "D6",
        "damage": "H",
        "cost_d4": 3,
        "cost_d6": 5,
        "cost_d8": 7,
        "cost_d10": 10,
        "cost_d12": 13
    },
    {
        "id": 86,
        "display_name": "Particle Bolter V",
        "name": "particle-bolter-5",
        "range": 34,
        "ap": "D8",
        "at": "D8",
        "aa": "D8",
        "damage": "H",
        "cost_d4": 6,
        "cost_d6": 8,
        "cost_d8": 11,
        "cost_d10": 15,
        "cost_d12": 18
    },
    {
        "id": 87,
        "display_name": "Plasma I",
        "name": "plasma-1",
        "range": 8,
        "ap": "D8",
        "at": "D10",
        "aa": "D10",
        "damage": "ML",
        "cost_d4": 2,
        "cost_d6": 2,
        "cost_d8": 3,
        "cost_d10": 4,
        "cost_d12": 4
    },
    {
        "id": 88,
        "display_name": "Plasma II",
        "name": "plasma-2",
        "range": 9,
        "ap": "D8",
        "at": "D10",
        "aa": "D10",
        "damage": "MH",
        "cost_d4": 2,
        "cost_d6": 3,
        "cost_d8": 4,
        "cost_d10": 4,
        "cost_d12": 5
    },
    {
        "id": 89,
        "display_name": "Plasma III",
        "name": "plasma-3",
        "range": 10,
        "ap": "D10",
        "at": "D12",
        "aa": "D12",
        "damage": "MH",
        "cost_d4": 3,
        "cost_d6": 4,
        "cost_d8": 4,
        "cost_d10": 5,
        "cost_d12": 6
    },
    {
        "id": 90,
        "display_name": "Plasma IV",
        "name": "plasma-4",
        "range": 11,
        "ap": "D10",
        "at": "D12",
        "aa": "D12",
        "damage": "H",
        "cost_d4": 4,
        "cost_d6": 5,
        "cost_d8": 6,
        "cost_d10": 7,
        "cost_d12": 7
    },
    {
        "id": 91,
        "display_name": "Plasma V",
        "name": "plasma-5",
        "range": 12,
        "ap": "D12",
        "at": "D12",
        "aa": "D12",
        "damage": "H",
        "cost_d4": 5,
        "cost_d6": 6,
        "cost_d8": 6,
        "cost_d10": 7,
        "cost_d12": 8
    },
    {
        "id": 92,
        "display_name": "Pulse Laser I",
        "name": "pulse-laser-1",
        "range": 24,
        "ap": "D4",
        "at": "D4",
        "aa": "D4",
        "damage": "L",
        "cost_d4": 1,
        "cost_d6": 1,
        "cost_d8": 2,
        "cost_d10": 2,
        "cost_d12": 2
    },
    {
        "id": 93,
        "display_name": "Pulse Laser II",
        "name": "pulse-laser-2",
        "range": 28,
        "ap": "D6",
        "at": "D4",
        "aa": "D4",
        "damage": "L",
        "cost_d4": 1,
        "cost_d6": 2,
        "cost_d8": 3,
        "cost_d10": 3,
        "cost_d12": 4
    },
    {
        "id": 94,
        "display_name": "Pulse Laser III",
        "name": "pulse-laser-3",
        "range": 32,
        "ap": "D8",
        "at": "D4",
        "aa": "D4",
        "damage": "ML",
        "cost_d4": 3,
        "cost_d6": 4,
        "cost_d8": 6,
        "cost_d10": 7,
        "cost_d12": 9
    },
    {
        "id": 95,
        "display_name": "Pulse Laser IV",
        "name": "pulse-laser-4",
        "range": 36,
        "ap": "D10",
        "at": "D6",
        "aa": "D6",
        "damage": "ML",
        "cost_d4": 5,
        "cost_d6": 7,
        "cost_d8": 8,
        "cost_d10": 10,
        "cost_d12": 11
    },
    {
        "id": 96,
        "display_name": "Pulse Laser V",
        "name": "pulse-laser-5",
        "range": 40,
        "ap": "D12",
        "at": "D6",
        "aa": "D6",
        "damage": "ML",
        "cost_d4": 6,
        "cost_d6": 8,
        "cost_d8": 10,
        "cost_d10": 12,
        "cost_d12": 13
    },
    {
        "id": 97,
        "display_name": "Railgun I",
        "name": "railgun-1",
        "range": 18,
        "ap": "D4",
        "at": "D4",
        "aa": "D4",
        "damage": "L",
        "cost_d4": 1,
        "cost_d6": 1,
        "cost_d8": 1,
        "cost_d10": 2,
        "cost_d12": 2
    },
    {
        "id": 98,
        "display_name": "Railgun II",
        "name": "railgun-2",
        "range": 27,
        "ap": "D4",
        "at": "D6",
        "aa": "D6",
        "damage": "ML",
        "cost_d4": 2,
        "cost_d6": 3,
        "cost_d8": 4,
        "cost_d10": 6,
        "cost_d12": 7
    },
    {
        "id": 99,
        "display_name": "Railgun III",
        "name": "railgun-3",
        "range": 36,
        "ap": "D4",
        "at": "D8",
        "aa": "D8",
        "damage": "MH",
        "cost_d4": 3,
        "cost_d6": 5,
        "cost_d8": 7,
        "cost_d10": 9,
        "cost_d12": 11
    },
    {
        "id": 100,
        "display_name": "Railgun IV",
        "name": "railgun-4",
        "range": 45,
        "ap": "D4",
        "at": "D10",
        "aa": "D10",
        "damage": "MH",
        "cost_d4": 5,
        "cost_d6": 7,
        "cost_d8": 10,
        "cost_d10": 13,
        "cost_d12": 15
    },
    {
        "id": 101,
        "display_name": "Railgun V",
        "name": "railgun-5",
        "range": 54,
        "ap": "D4",
        "at": "D12",
        "aa": "D12",
        "damage": "H",
        "cost_d4": 11,
        "cost_d6": 13,
        "cost_d8": 16,
        "cost_d10": 21,
        "cost_d12": 24
    },
    {
        "id": 102,
        "display_name": "Rockets I",
        "name": "rockets-1",
        "range": 20,
        "ap": "D4",
        "at": "D4",
        "aa": "D4",
        "damage": "L",
        "cost_d4": 1,
        "cost_d6": 1,
        "cost_d8": 2,
        "cost_d10": 2,
        "cost_d12": 2,
        "is_indirect": true
    },
    {
        "id": 103,
        "display_name": "Rockets II",
        "name": "rockets-2",
        "range": 24,
        "ap": "D6",
        "at": "D6",
        "aa": "D6",
        "damage": "L",
        "cost_d4": 1,
        "cost_d6": 3,
        "cost_d8": 3,
        "cost_d10": 4,
        "cost_d12": 4,
        "is_indirect": true
    },
    {
        "id": 104,
        "display_name": "Rockets III",
        "name": "rockets-3",
        "range": 28,
        "ap": "D6",
        "at": "D6",
        "aa": "D6",
        "damage": "ML",
        "cost_d4": 2,
        "cost_d6": 4,
        "cost_d8": 6,
        "cost_d10": 7,
        "cost_d12": 9,
        "is_indirect": true
    },
    {
        "id": 105,
        "display_name": "Rockets IV",
        "name": "rockets-4",
        "range": 32,
        "ap": "D8",
        "at": "D8",
        "aa": "D8",
        "damage": "ML",
        "cost_d4": 5,
        "cost_d6": 7,
        "cost_d8": 9,
        "cost_d10": 11,
        "cost_d12": 12,
        "is_indirect": true
    },
    {
        "id": 106,
        "display_name": "Rockets V",
        "name": "rockets-5",
        "range": 36,
        "ap": "D10",
        "at": "D10",
        "aa": "D10",
        "damage": "ML",
        "cost_d4": 8,
        "cost_d6": 11,
        "cost_d8": 13,
        "cost_d10": 15,
        "cost_d12": 17,
        "is_indirect": true
    }
]
