{
    "chem-spray-1": {
        "slug": "chem-spray-1",
        "aa": "D4",
        "at": "D4",
        "ap": "D6",
        "name": "Inf Chem Spray I",
        "range": 2,
        "damage": "L"
    },
    "chem-spray-2": {
        "slug": "chem-spray-2",
        "aa": "D6",
        "at": "D6",
        "ap": "D8",
        "name": "Inf Chem Spray II",
        "range": 3,
        "damage": "L"
    },
    "chem-spray-3": {
        "slug": "chem-spray-3",
        "aa": "D8",
        "at": "D8",
        "ap": "D10",
        "name": "Inf Chem Spray III",
        "range": 4,
        "damage": "ML"
    },
    "flamethrower-1": {
        "slug": "flamethrower-1",
        "aa": "D4",
        "at": "D4",
        "ap": "D8",
        "name": "Inf Flamethrower I",
        "range": 2,
        "damage": "ML"
    },
    "flamethrower-2": {
        "slug": "flamethrower-2",
        "aa": "D4",
        "at": "D4",
        "ap": "D8",
        "name": "Inf Flamethrower II",
        "range": 3,
        "damage": "ML"
    },
    "flamethrower-3": {
        "slug": "flamethrower-3",
        "aa": "D6",
        "at": "D6",
        "ap": "D10",
        "name": "Inf Flamethrower III",
        "range": 4,
        "damage": "MH"
    },
    "laser-1": {
        "slug": "laser-1",
        "aa": "D4",
        "at": "D4",
        "ap": "D6",
        "name": "Inf Laser I",
        "range": 24,
        "damage": "ML"
    },
    "laser-2": {
        "slug": "laser-2",
        "aa": "D6",
        "at": "D6",
        "ap": "D8",
        "name": "Inf Laser II",
        "range": 30,
        "damage": "MH"
    },
    "laser-3": {
        "slug": "laser-3",
        "aa": "D8",
        "at": "D8",
        "ap": "D10",
        "name": "Inf Laser III",
        "range": 36,
        "damage": "H"
    },
    "laser-small-arms-1": {
        "slug": "laser-small-arms-1",
        "aa": "NONE",
        "at": "D4",
        "ap": "D4",
        "name": "Laser Sm Arms I",
        "range": 12,
        "damage": "L"
    },
    "laser-small-arms-2": {
        "slug": "laser-small-arms-2",
        "aa": "NONE",
        "at": "D6",
        "ap": "D4",
        "name": "Laser Sm Arms II",
        "range": 14,
        "damage": "L"
    },
    "laser-small-arms-3": {
        "slug": "laser-small-arms-3",
        "aa": "NONE",
        "at": "D8",
        "ap": "D6",
        "name": "Laser Sm Arms III",
        "range": 16,
        "damage": "ML"
    },
    "machine-gun-1": {
        "slug": "machine-gun-1",
        "aa": "NONE",
        "at": "D4",
        "ap": "D6",
        "name": "Inf MG I",
        "range": 7,
        "damage": "L"
    },
    "machine-gun-2": {
        "slug": "machine-gun-2",
        "aa": "NONE",
        "at": "D6",
        "ap": "D8",
        "name": "Inf MG II",
        "range": 10,
        "damage": "L"
    },
    "machine-gun-3": {
        "slug": "machine-gun-3",
        "aa": "NONE",
        "at": "D8",
        "ap": "D10",
        "name": "Inf MG III",
        "range": 13,
        "damage": "ML"
    },
    "missile-launcher-1": {
        "slug": "missile-launcher-1",
        "aa": "NONE",
        "at": "D6",
        "ap": "D4",
        "is_indirect": true,
        "name": "Inf Missile I",
        "range": 20,
        "damage": "L"
    },
    "missile-launcher-2": {
        "slug": "missile-launcher-2",
        "aa": "NONE",
        "at": "D8",
        "ap": "D6",
        "is_indirect": true,
        "name": "Inf Missile II",
        "range": 24,
        "damage": "ML"
    },
    "missile-launcher-3": {
        "slug": "missile-launcher-3",
        "aa": "NONE",
        "at": "D10",
        "ap": "D8",
        "is_indirect": true,
        "name": "Inf Missile III",
        "range": 28,
        "damage": "MH"
    },
    "mortar-1": {
        "slug": "mortar-1",
        "aa": "NONE",
        "at": "D4",
        "ap": "D4",
        "is_indirect": true,
        "name": "Inf Mortar I",
        "range": 10,
        "damage": "ML"
    },
    "mortar-2": {
        "slug": "mortar-2",
        "aa": "NONE",
        "at": "D4",
        "ap": "D4",
        "is_indirect": true,
        "name": "Inf Mortar II",
        "range": 14,
        "damage": "ML"
    },
    "mortar-3": {
        "slug": "mortar-3",
        "aa": "NONE",
        "at": "D6",
        "ap": "D6",
        "is_indirect": true,
        "name": "Inf Mortar III",
        "range": 18,
        "damage": "MH"
    },
    "plasma-1": {
        "slug": "plasma-1",
        "aa": "NONE",
        "at": "D8",
        "ap": "D8",
        "name": "Inf Plasma I",
        "range": 4,
        "damage": "ML"
    },
    "plasma-2": {
        "slug": "plasma-2",
        "aa": "NONE",
        "at": "D10",
        "ap": "D10",
        "name": "Inf Plasma II",
        "range": 5,
        "damage": "ML"
    },
    "plasma-3": {
        "slug": "plasma-3",
        "aa": "NONE",
        "at": "D12",
        "ap": "D12",
        "name": "Inf Plasma III",
        "range": 6,
        "damage": "MH"
    },
    "pulse-laser-1": {
        "slug": "pulse-laser-1",
        "aa": "NONE",
        "at": "D4",
        "ap": "D4",
        "name": "Inf Pulse Laser I",
        "range": 24,
        "damage": "L"
    },
    "pulse-laser-2": {
        "slug": "pulse-laser-2",
        "aa": "NONE",
        "at": "D4",
        "ap": "D6",
        "name": "Inf Pulse Laser II",
        "range": 30,
        "damage": "L"
    },
    "pulse-laser-3": {
        "slug": "pulse-laser-3",
        "aa": "NONE",
        "at": "D4",
        "ap": "D8",
        "name": "Inf Pulse Laser III",
        "range": 36,
        "damage": "L"
    },
    "small-arms-1": {
        "slug": "small-arms-1",
        "aa": "NONE",
        "at": "D4",
        "ap": "D4",
        "name": "Small Arms I",
        "range": 6,
        "damage": "L"
    },
    "small-arms-2": {
        "slug": "small-arms-2",
        "aa": "NONE",
        "at": "D6",
        "ap": "D6",
        "name": "Small Arms II",
        "range": 8,
        "damage": "ML"
    },
    "small-arms-3": {
        "slug": "small-arms-3",
        "aa": "NONE",
        "at": "D8",
        "ap": "D8",
        "name": "Small Arms III",
        "range": 10,
        "damage": "MH"
    }
}
